flask_admin_cli/__init__.py
flask_admin_cli/api.py
flask_admin_cli/cli.py
flask_admin_cli/exceptions.py
flask_admin_cli-0.1.4.dist-info/entry_points.txt
flask_admin_cli-0.1.4.dist-info/METADATA
flask_admin_cli-0.1.4.dist-info/WHEEL
flask_admin_cli-0.1.4.dist-info/RECORD
