Metadata-Version: 2.1
Name: flask-admin-cli
Version: 0.1.4
Summary: A CLI application to create Flask Admin instances.
Home-page: https://mariofix.github.io/flask-admin-cli/
License: MIT
Keywords: flask-admin,cli,python,console,click
Author: Mario Hernandez
Author-email: mariofix@proton.me
Requires-Python: >=3.7,<4.0
Classifier: Development Status :: 4 - Beta
Classifier: Environment :: Console
Classifier: Framework :: Flask
Classifier: Intended Audience :: Developers
Classifier: License :: OSI Approved :: MIT License
Classifier: Operating System :: OS Independent
Classifier: Programming Language :: Python :: 3
Classifier: Programming Language :: Python :: 3.7
Classifier: Programming Language :: Python :: 3.8
Classifier: Programming Language :: Python :: 3.9
Classifier: Programming Language :: Python :: 3.10
Classifier: Programming Language :: Python :: 3.11
Classifier: Programming Language :: Python :: 3
Classifier: Topic :: Software Development :: Build Tools
Classifier: Topic :: Software Development :: Code Generators
Classifier: Topic :: Software Development :: Libraries :: Python Modules
Classifier: Topic :: System :: Installation/Setup
Classifier: Topic :: Utilities
Requires-Dist: click (>=8.1.3,<9.0.0)
Project-URL: Documentation, https://mariofix.github.io/flask-admin-cli/
Project-URL: Repository, https://github.com/mariofix/flask-admin-cli
